simcore_wrapper/__init__.py
simcore_wrapper/core.py
simcore_wrapper-0.1.dist-info/METADATA
simcore_wrapper-0.1.dist-info/WHEEL
simcore_wrapper-0.1.dist-info/top_level.txt
simcore_wrapper-0.1.dist-info/RECORD
