Metadata-Version: 2.1
Name: simcore_wrapper
Version: 0.1
Summary: A Python wrapper for the sim-core Kotlin library
License: MIT
Requires-Dist: jpype1
